minineedle/__init__.py
minineedle/core.py
minineedle/needle.py
minineedle/smith.py
minineedle/typesvars.py
minineedle-3.1.5.dist-info/LICENSE
minineedle-3.1.5.dist-info/METADATA
minineedle-3.1.5.dist-info/WHEEL
minineedle-3.1.5.dist-info/RECORD
