Metadata-Version: 2.1
Name: minineedle
Version: 3.1.5
Summary: Needleman-Wunsch and Smith-Waterman algorithms in python for any iterable objects.
Home-page: https://github.com/scastlara/minineedle
License: GPL3
Author: S. Castillo-Lara
Author-email: sergiocastillo@ub.edu
Requires-Python: >=3.9
Classifier: License :: Other/Proprietary License
Classifier: Programming Language :: Python :: 3
Classifier: Programming Language :: Python :: 3.9
Classifier: Programming Language :: Python :: 3.10
Classifier: Programming Language :: Python :: 3.11
Project-URL: Repository, https://github.com/scastlara/minineedle
